p5/__init__.py
p5/__main__.py
p5/color.py
p5/constants.py
p5/corefunctions.py
p5/mathfunctions.py
p5/p5-python.png
p5/renderer.py
p5/settings.py
p5/timedata.py
p5/transform.py
p5_python-0.6.29.dist-info/METADATA
p5_python-0.6.29.dist-info/WHEEL
p5_python-0.6.29.dist-info/top_level.txt
p5_python-0.6.29.dist-info/RECORD
