Metadata-Version: 2.1
Name: p5-python
Version: 0.6.29
Summary: A package wrapping pygame functionality in p5.js calling conventions.
Home-page: https://github.com/gromko/p5-python
Author: Grygoriy Gromko
Author-email: gr.gromko@gmail.com
Maintainer: Grygoriy Gromko
Maintainer-email: gr.gromko@gmail.com
Requires-Python: >=3.8.0
Requires-Dist: pycairo (>=1.20.0)
Requires-Dist: pygame (<3.0.0,>=2.1.2)
